anilibria/__init__.py
anilibria/client.py
anilibria/exceptions.py
anilibria/models.py
anilibria/rest_adapter.py
anilibria-0.1.8.dist-info/LICENSE
anilibria-0.1.8.dist-info/METADATA
anilibria-0.1.8.dist-info/WHEEL
anilibria-0.1.8.dist-info/RECORD
