Metadata-Version: 2.3
Name: anilibria
Version: 0.1.8
Summary: Python API wrapper for AniLibria
License: MIT
Author: anekobtw
Author-email: krolexonder@gmail.com
Requires-Python: >=3.9
Classifier: License :: OSI Approved :: MIT License
Classifier: Programming Language :: Python :: 3
Classifier: Programming Language :: Python :: 3.9
Classifier: Programming Language :: Python :: 3.10
Classifier: Programming Language :: Python :: 3.11
Classifier: Programming Language :: Python :: 3.12
Classifier: Programming Language :: Python :: 3.13
Requires-Dist: m3u8-to-mp4 (>=0.1.11,<0.2.0)
Requires-Dist: requests (>=2.32.3,<3.0.0)
